LICENSE
MANIFEST.in
README.md
setup.py
celery_task_tigger.egg-info/PKG-INFO
celery_task_tigger.egg-info/SOURCES.txt
celery_task_tigger.egg-info/dependency_links.txt
celery_task_tigger.egg-info/top_level.txt
celery_tasktigger/__init__.py
celery_tasktigger/decorator.py